openai_billing/__init__.py
openai_billing/__main__.py
openai_billing/get_browser.py
openai_billing/openai_billing.py
openai_billing-0.1.0a2.dist-info/entry_points.txt
openai_billing-0.1.0a2.dist-info/LICENSE
openai_billing-0.1.0a2.dist-info/METADATA
openai_billing-0.1.0a2.dist-info/WHEEL
openai_billing-0.1.0a2.dist-info/RECORD
