Metadata-Version: 2.1
Name: openai-billing
Version: 0.1.0a2
Summary: Fetch openai billing info from command line
Home-page: https://github.com/ffreemt/openai-billing-playwright
License: MIT
Author: ffreemt
Requires-Python: >=3.8,<4.0
Classifier: License :: OSI Approved :: MIT License
Classifier: Programming Language :: Python :: 3
Classifier: Programming Language :: Python :: 3.8
Classifier: Programming Language :: Python :: 3.9
Classifier: Programming Language :: Python :: 3.10
Classifier: Programming Language :: Python :: 3.11
Requires-Dist: charset-normalizer (>=3.2.0,<4.0.0)
Requires-Dist: loguru (>=0.7.0,<0.8.0)
Requires-Dist: playwright (>=1.37.0,<2.0.0)
Requires-Dist: pyperclip (>=1.8.2,<2.0.0)
Requires-Dist: rich (>=13.5.2,<14.0.0)
Requires-Dist: typer (>=0.9.0,<0.10.0)
Project-URL: Repository, https://github.com/ffreemt/openai-billing-playwright
